commandrex_cli/__init__.py
commandrex_cli/config.py
commandrex_cli/executor.py
commandrex_cli/history.py
commandrex_cli/input_handler.py
commandrex_cli/main.py
commandrex_cli/platform_utils.py
commandrex_cli/schemas.py
commandrex_cli/translator.py
commandrex_cli/ui.py
commandrex_cli-0.3.0.dist-info/entry_points.txt
commandrex_cli-0.3.0.dist-info/LICENCE
commandrex_cli-0.3.0.dist-info/METADATA
commandrex_cli-0.3.0.dist-info/WHEEL
commandrex_cli-0.3.0.dist-info/RECORD
