Metadata-Version: 2.1
Name: commandrex-cli
Version: 0.3.0
Summary: A natural language interface for terminal commands
License: MIT
Keywords: cli,terminal,natural-language,openai,commands
Author: Siddhant
Author-email: siddhantg314@gmail.com
Requires-Python: >=3.9,<4.0
Classifier: Development Status :: 4 - Beta
Classifier: Environment :: Console
Classifier: Intended Audience :: Developers
Classifier: Intended Audience :: System Administrators
Classifier: License :: OSI Approved :: MIT License
Classifier: Operating System :: OS Independent
Classifier: Programming Language :: Python :: 3
Classifier: Programming Language :: Python :: 3.9
Classifier: Programming Language :: Python :: 3.10
Classifier: Programming Language :: Python :: 3.11
Classifier: Programming Language :: Python :: 3.12
Classifier: Programming Language :: Python :: 3.13
Classifier: Programming Language :: Python :: 3.8
Classifier: Topic :: System :: Shells
Classifier: Topic :: Utilities
Requires-Dist: colorama (>=0.4.6,<0.5.0)
Requires-Dist: httpx (>=0.27.2,<0.28.0)
Requires-Dist: keyring (>=25.5.0,<26.0.0)
Requires-Dist: openai (>=1.54.3,<2.0.0)
Requires-Dist: prompt-toolkit (>=3.0.39,<4.0.0)
Requires-Dist: pydantic (>=2.9.2,<3.0.0)
Requires-Dist: python-dotenv (>=1.0.1,<2.0.0)
Requires-Dist: rich (>=13.9.4,<14.0.0)
Requires-Dist: typing-extensions (>=4.12.2,<5.0.0)
